mal_scraper/__init__.py
mal_scraper/anime.py
mal_scraper/consts.py
mal_scraper/exceptions.py
mal_scraper/mal_utils.py
mal_scraper/requester.py
mal_scraper/users.py
mal_scraper-0.3.0.dist-info/DESCRIPTION.rst
mal_scraper-0.3.0.dist-info/METADATA
mal_scraper-0.3.0.dist-info/RECORD
mal_scraper-0.3.0.dist-info/WHEEL
mal_scraper-0.3.0.dist-info/metadata.json
mal_scraper-0.3.0.dist-info/top_level.txt
