Metadata-Version: 2.0
Name: mal-scraper
Version: 0.3.0
Summary: MyAnimeList web scraper
Home-page: https://github.com/QasimK/mal-scraper
Author: Qasim K
Author-email: QasimK@users.noreply.github.com
License: MIT
Platform: UNKNOWN
Classifier: Development Status :: 2 - Pre-Alpha
Classifier: Framework :: Pytest
Classifier: Framework :: Sphinx
Classifier: Intended Audience :: Developers
Classifier: License :: OSI Approved :: MIT License
Classifier: Natural Language :: English
Classifier: Operating System :: OS Independent
Classifier: Programming Language :: Python
Classifier: Programming Language :: Python :: 3
Classifier: Programming Language :: Python :: 3.4
Classifier: Programming Language :: Python :: 3.5
Classifier: Topic :: Utilities
Classifier: Topic :: Internet
Classifier: Topic :: Software Development :: Libraries
Requires-Dist: beautifulsoup4 (>=4,<5)
Requires-Dist: requests (>=2,<3)
Provides-Extra: develop
Requires-Dist: bumpversion; extra == 'develop'
Requires-Dist: pytest; extra == 'develop'
Requires-Dist: responses (>=0,<1); extra == 'develop'
Requires-Dist: tox; extra == 'develop'
